ioscodesign/__init__.py
ioscodesign/cmd.py
ioscodesign/codesign.py
ioscodesign/keychain.py
ioscodesign/mobileprovision.py
ioscodesign-1.0.3.dist-info/DESCRIPTION.rst
ioscodesign-1.0.3.dist-info/METADATA
ioscodesign-1.0.3.dist-info/RECORD
ioscodesign-1.0.3.dist-info/WHEEL
ioscodesign-1.0.3.dist-info/entry_points.txt
ioscodesign-1.0.3.dist-info/metadata.json
ioscodesign-1.0.3.dist-info/top_level.txt
