Metadata-Version: 2.0
Name: ioscodesign
Version: 1.0.3
Summary: codesign tool for iOS package
Home-page: https://github.com/oylbin/iOSCodeSign
Author: oylbin
Author-email: oylbin@gmail.com
License: Apache Software License
Keywords: ios codesign codesigning
Platform: UNKNOWN
Classifier: Development Status :: 4 - Beta
Classifier: Intended Audience :: Developers
Classifier: Topic :: Software Development :: Build Tools
Classifier: License :: OSI Approved :: Apache Software License
Classifier: Operating System :: MacOS
Classifier: Operating System :: MacOS :: MacOS X
Classifier: Programming Language :: Python :: 3
Classifier: Programming Language :: Python :: 3.5
Requires-Dist: click
Requires-Dist: sh
